odoo/addons/sale_stock_available_to_promise_release_cutoff/README.rst
odoo/addons/sale_stock_available_to_promise_release_cutoff/__init__.py
odoo/addons/sale_stock_available_to_promise_release_cutoff/__manifest__.py
odoo/addons/sale_stock_available_to_promise_release_cutoff/i18n/pt_BR.po
odoo/addons/sale_stock_available_to_promise_release_cutoff/i18n/sale_stock_available_to_promise_release_cutoff.pot
odoo/addons/sale_stock_available_to_promise_release_cutoff/models/__init__.py
odoo/addons/sale_stock_available_to_promise_release_cutoff/models/sale_order.py
odoo/addons/sale_stock_available_to_promise_release_cutoff/models/sale_order_line.py
odoo/addons/sale_stock_available_to_promise_release_cutoff/readme/CONTRIBUTORS.rst
odoo/addons/sale_stock_available_to_promise_release_cutoff/readme/CREDITS.rst
odoo/addons/sale_stock_available_to_promise_release_cutoff/readme/DESCRIPTION.rst
odoo/addons/sale_stock_available_to_promise_release_cutoff/static/description/icon.png
odoo/addons/sale_stock_available_to_promise_release_cutoff/static/description/index.html
odoo14_addon_sale_stock_available_to_promise_release_cutoff-14.0.1.1.1.dist-info/METADATA
odoo14_addon_sale_stock_available_to_promise_release_cutoff-14.0.1.1.1.dist-info/WHEEL
odoo14_addon_sale_stock_available_to_promise_release_cutoff-14.0.1.1.1.dist-info/top_level.txt
odoo14_addon_sale_stock_available_to_promise_release_cutoff-14.0.1.1.1.dist-info/RECORD
